vgpt/__init__.py
vgpt/__main__.py
vgpt/app.py
vgpt/config.py
vgpt/gcp.py
vgpt/log.py
vgpt/roles.py
vgpt/version.py
vgpt-0.2.0.dist-info/LICENSE
vgpt-0.2.0.dist-info/METADATA
vgpt-0.2.0.dist-info/WHEEL
vgpt-0.2.0.dist-info/entry_points.txt
vgpt-0.2.0.dist-info/RECORD
