Metadata-Version: 2.1
Name: vgpt
Version: 0.2.0
Summary: a command line interface for google cloud platform' 's vertex ai chat bot
License: GNU GPL v3.0
Author: Will Wright
Author-email: will.wright.engineering@gmail.com
Requires-Python: >=3.8,<4.0
Classifier: License :: Other/Proprietary License
Classifier: Programming Language :: Python :: 3
Classifier: Programming Language :: Python :: 3.8
Classifier: Programming Language :: Python :: 3.9
Classifier: Programming Language :: Python :: 3.10
Classifier: Programming Language :: Python :: 3.11
Requires-Dist: distro (>=1.8.0,<2.0.0)
Requires-Dist: google-auth (>=2.23.3,<3.0.0)
Requires-Dist: python-dotenv (>=1.0.0,<2.0.0)
Requires-Dist: requests (>=2.31.0,<3.0.0)
Requires-Dist: toml (>=0.10.2,<0.11.0)
Requires-Dist: typer[all] (>=0.9.0,<0.10.0)
